asreview_insights-1.6.1.dist-info/licenses/LICENSE
asreviewcontrib/insights/__init__.py
asreviewcontrib/insights/algorithms.py
asreviewcontrib/insights/entrypoint.py
asreviewcontrib/insights/metrics.py
asreviewcontrib/insights/plot.py
asreviewcontrib/insights/utils.py
asreview_insights-1.6.1.dist-info/METADATA
asreview_insights-1.6.1.dist-info/WHEEL
asreview_insights-1.6.1.dist-info/entry_points.txt
asreview_insights-1.6.1.dist-info/top_level.txt
asreview_insights-1.6.1.dist-info/RECORD
