Metadata-Version: 2.4
Name: asreview-insights
Version: 1.6.1
Summary: Insights and plotting tool for the ASReview project
Author-email: ASReview LAB developers <asreview@uu.nl>
License: Apache-2.0
Project-URL: homepage, https://asreview.ai
Project-URL: repository, https://github.com/asreview/asreview-insights
Classifier: Development Status :: 4 - Beta
Classifier: License :: OSI Approved :: Apache Software License
Classifier: Programming Language :: Python :: 3.10
Classifier: Programming Language :: Python :: 3.11
Classifier: Programming Language :: Python :: 3.12
Classifier: Programming Language :: Python :: 3.13
Requires-Python: >=3.10
License-File: LICENSE
Requires-Dist: numpy
Requires-Dist: matplotlib
Requires-Dist: asreview<3,>=2
Provides-Extra: lint
Requires-Dist: ruff; extra == "lint"
Provides-Extra: test
Requires-Dist: pytest; extra == "test"
Dynamic: license-file
